AUTHORS
ChangeLog
MANIFEST.in
README.rst
requirements.txt
setup.cfg
setup.py
leonardo_team.egg-info/PKG-INFO
leonardo_team.egg-info/SOURCES.txt
leonardo_team.egg-info/dependency_links.txt
leonardo_team.egg-info/not-zip-safe
leonardo_team.egg-info/pbr.json
leonardo_team.egg-info/requires.txt
leonardo_team.egg-info/top_level.txt
team/__init__.py
team/admin.py
team/models.py
team/views.py
team/apps/__init__.py
team/apps/team.py
team/locale/cs/LC_MESSAGES/django.po
team/locale/en/LC_MESSAGES/django.po
team/locale/ru/LC_MESSAGES/django.po
team/migrations/0001_initial.py
team/migrations/__init__.py
team/templates/team/person_detail.html
team/templates/team/person_list.html
team/templates/widget/team/default.html
team/widget/__init__.py
team/widget/team/__init__.py
team/widget/team/models.py